odoo/addons/fieldservice_purchase/README.rst
odoo/addons/fieldservice_purchase/__init__.py
odoo/addons/fieldservice_purchase/__manifest__.py
odoo/addons/fieldservice_purchase/i18n/de.po
odoo/addons/fieldservice_purchase/i18n/es_AR.po
odoo/addons/fieldservice_purchase/i18n/es_CL.po
odoo/addons/fieldservice_purchase/i18n/fieldservice_purchase.pot
odoo/addons/fieldservice_purchase/i18n/fr_FR.po
odoo/addons/fieldservice_purchase/i18n/it.po
odoo/addons/fieldservice_purchase/i18n/pt_BR.po
odoo/addons/fieldservice_purchase/i18n/pt_PT.po
odoo/addons/fieldservice_purchase/i18n/tr.po
odoo/addons/fieldservice_purchase/models/__init__.py
odoo/addons/fieldservice_purchase/models/fsm_person.py
odoo/addons/fieldservice_purchase/readme/CONTRIBUTORS.rst
odoo/addons/fieldservice_purchase/readme/CREDITS.rst
odoo/addons/fieldservice_purchase/readme/DESCRIPTION.rst
odoo/addons/fieldservice_purchase/readme/ROADMAP.rst
odoo/addons/fieldservice_purchase/readme/USAGE.rst
odoo/addons/fieldservice_purchase/security/ir.model.access.csv
odoo/addons/fieldservice_purchase/static/description/icon.png
odoo/addons/fieldservice_purchase/static/description/index.html
odoo/addons/fieldservice_purchase/tests/__init__.py
odoo/addons/fieldservice_purchase/tests/test_fieldservice_purchase.py
odoo/addons/fieldservice_purchase/views/fsm_person.xml
odoo13_addon_fieldservice_purchase-13.0.1.0.1.dev15.dist-info/METADATA
odoo13_addon_fieldservice_purchase-13.0.1.0.1.dev15.dist-info/WHEEL
odoo13_addon_fieldservice_purchase-13.0.1.0.1.dev15.dist-info/top_level.txt
odoo13_addon_fieldservice_purchase-13.0.1.0.1.dev15.dist-info/RECORD
